{
  "slug": "diego-gonzález",
  "display_name": "Diego González",
  "shirt_no": null,
  "position_code": "MF",
  "dob": "2003-01-07",
  "age": 23,
  "caps": 4,
  "goals": 0,
  "club_from_squad_table": "Atlas",
  "wikipedia_title": "Diego González (footballer, born 2003)",
  "date_of_birth": "2003-01-07",
  "date_of_birth_source": "wikipedia-squad-table",
  "current_club": "Atlas",
  "current_club_source": "wikipedia-squad-table",
  "wikidata_qid": "Q116433960",
  "qid": "Q116433960",
  "name": "Diego González",
  "description": "Paraguayan footballer (born 2003)",
  "citizenship_qids": [
    "Q733"
  ],
  "height_cm": 168.0,
  "image_filename": "Atlas Diego González.jpg",
  "wikipedia_url": "https://en.wikipedia.org/wiki/Diego_Gonz%C3%A1lez_(footballer,_born_2003)",
  "transfermarkt_id": "873981",
  "citizenship": [
    "Paraguay"
  ],
  "photo": {
    "filename": "Atlas Diego González.jpg",
    "url": "https://upload.wikimedia.org/wikipedia/commons/6/6f/Atlas_Diego_Gonz%C3%A1lez.jpg",
    "thumb_url": "https://upload.wikimedia.org/wikipedia/commons/thumb/6/6f/Atlas_Diego_Gonz%C3%A1lez.jpg/960px-Atlas_Diego_Gonz%C3%A1lez.jpg",
    "width": 1050,
    "height": 1400,
    "license": "CC BY 4.0",
    "license_url": "https://creativecommons.org/licenses/by/4.0",
    "attribution": "<a href=\"//commons.wikimedia.org/wiki/User:Keiteay\" title=\"User:Keiteay\">Keiteay</a>",
    "source": "wikidata-p18",
    "local_path": "data/photos/diego-gonzález.jpg"
  },
  "team_slug": "paraguay",
  "team_country": "Paraguay"
}
