{
  "slug": "mateo-kova\u010di\u0107",
  "display_name": "Mateo Kova\u010di\u0107",
  "shirt_no": null,
  "position_code": "MF",
  "dob": "1994-05-06",
  "age": 32,
  "caps": 111,
  "goals": 5,
  "club_from_squad_table": "Manchester City",
  "wikipedia_title": "Mateo Kova\u010di\u0107",
  "date_of_birth": "1994-05-06",
  "date_of_birth_source": "wikipedia-squad-table",
  "current_club": "Manchester City",
  "current_club_source": "wikipedia-squad-table",
  "wikidata_qid": "Q701297",
  "qid": "Q701297",
  "name": "Mateo Kova\u010di\u0107",
  "description": "Croatian association football player (born 1994)",
  "place_of_birth_qid": "Q41329",
  "citizenship_qids": [
    "Q224"
  ],
  "height_cm": 177.0,
  "weight_kg": 75.0,
  "position_qids": [
    "Q193592"
  ],
  "teams": [
    {
      "team_qid": "Q172803",
      "start": "2010-00-00",
      "end": "2013-00-00"
    },
    {
      "team_qid": "Q8682",
      "start": "2015-01-01",
      "end": "2019-00-00"
    },
    {
      "team_qid": "Q631",
      "start": "2013-01-01",
      "end": "2015-01-01"
    },
    {
      "team_qid": "Q3589940",
      "start": "2009-01-01",
      "end": "2011-01-01"
    },
    {
      "team_qid": "Q134479",
      "start": "2013-01-01",
      "end": null
    },
    {
      "team_qid": "Q3446766",
      "start": "2009-01-01",
      "end": "2010-01-01"
    },
    {
      "team_qid": "Q2331381",
      "start": "2010-01-01",
      "end": "2014-01-01"
    },
    {
      "team_qid": "Q9616",
      "start": "2018-00-00",
      "end": "2019-00-00"
    },
    {
      "team_qid": "Q9616",
      "start": "2019-00-00",
      "end": "2023-00-00"
    },
    {
      "team_qid": "Q50602",
      "start": "2023-00-00",
      "end": null
    }
  ],
  "current_club_qid": "Q50602",
  "image_filename": "Chelsea vs. Arsenal, 29 May 2019 18 Kovacic.jpg",
  "wikipedia_url": "https://en.wikipedia.org/wiki/Mateo_Kova%C4%8Di%C4%87",
  "transfermarkt_id": "51471",
  "fifa_player_id": "339987",
  "positions": [
    "midfielder"
  ],
  "citizenship": [
    "Croatia"
  ],
  "place_of_birth": "Linz",
  "wikidata_current_club": "Manchester City F.C.",
  "wikidata_current_club_qid": "Q50602",
  "photo": {
    "filename": "Chelsea vs. Arsenal, 29 May 2019 18 Kovacic.jpg",
    "url": "https://upload.wikimedia.org/wikipedia/commons/d/d9/Chelsea_vs._Arsenal%2C_29_May_2019_18_Kovacic.jpg",
    "thumb_url": "https://upload.wikimedia.org/wikipedia/commons/d/d9/Chelsea_vs._Arsenal%2C_29_May_2019_18_Kovacic.jpg",
    "width": 356,
    "height": 484,
    "license": "CC BY 4.0",
    "license_url": "https://creativecommons.org/licenses/by/4.0",
    "attribution": "Amir Hosseini",
    "source": "wikidata-p18",
    "local_path": "data/photos/mateo-kova\u010di\u0107.jpg"
  },
  "team_slug": "croatia",
  "team_country": "Croatia"
}