{
  "slug": "matěj-kovář",
  "display_name": "Matěj Kovář",
  "shirt_no": null,
  "position_code": "GK",
  "dob": "2000-05-17",
  "age": 26,
  "caps": 19,
  "goals": 0,
  "club_from_squad_table": "PSV Eindhoven",
  "current_club": "PSV Eindhoven",
  "current_club_source": "wikipedia-squad-table",
  "wikipedia_title": "Matěj Kovář",
  "wikipedia_url": "https://en.wikipedia.org/wiki/Matěj_Kovář",
  "wikidata_qid": "Q59914031",
  "qid": "Q59914031",
  "date_of_birth": "2000-05-17",
  "positions": [
    "goalkeeper"
  ],
  "citizenship": [
    "Czech Republic"
  ],
  "image_filename": "Matj_kova-1772635856_(cropped).JPG",
  "photo": {
    "filename": "Matj_kova-1772635856_(cropped).JPG",
    "url": "https://upload.wikimedia.org/wikipedia/commons/b/bb/Matj_kova-1772635856_%28cropped%29.JPG",
    "thumb_url": "https://upload.wikimedia.org/wikipedia/commons/thumb/b/bb/Matj_kova-1772635856_%28cropped%29.JPG/960px-Matj_kova-1772635856_%28cropped%29.JPG",
    "width": 4378,
    "height": 3588,
    "license": "CC BY-SA 4.0",
    "license_url": "https://creativecommons.org/licenses/by-sa/4.0",
    "attribution": "Hans Reefman",
    "source": "wikipedia-pageimage",
    "local_path": "data/photos/matěj-kovář.jpg"
  },
  "team_slug": "czech-republic",
  "team_country": "Czech Republic"
}