{
  "slug": "sherel-floranus",
  "display_name": "Sherel Floranus",
  "shirt_no": null,
  "position_code": "DF",
  "dob": "1998-08-23",
  "age": 27,
  "caps": 26,
  "goals": 0,
  "club_from_squad_table": "PEC Zwolle",
  "wikipedia_title": "Sherel Floranus",
  "date_of_birth": "1998-08-23",
  "date_of_birth_source": "wikipedia-squad-table",
  "current_club": "PEC Zwolle",
  "current_club_source": "wikipedia-squad-table",
  "wikidata_qid": "Q20972384",
  "qid": "Q20972384",
  "name": "Sherel Floranus",
  "description": "Curaçaoan footballer",
  "place_of_birth_qid": "Q34370",
  "citizenship_qids": [
    "Q29999"
  ],
  "height_cm": 181.0,
  "position_qids": [
    "Q90173132"
  ],
  "teams": [
    {
      "team_qid": "Q209895",
      "start": "2015-01-01",
      "end": null
    },
    {
      "team_qid": "Q601723",
      "start": "2014-01-01",
      "end": null
    },
    {
      "team_qid": "Q1811026",
      "start": null,
      "end": null
    }
  ],
  "current_club_qid": "Q209895",
  "image_filename": "Sherel Floranus at Antalyaspor vs Fatih Karagümrük SK 20220213.jpg",
  "wikipedia_url": "https://en.wikipedia.org/wiki/Sherel_Floranus",
  "transfermarkt_id": "315211",
  "positions": [
    "full-back"
  ],
  "citizenship": [
    "Kingdom of the Netherlands"
  ],
  "place_of_birth": "Rotterdam",
  "wikidata_current_club": "Sparta Rotterdam",
  "wikidata_current_club_qid": "Q209895",
  "photo": {
    "filename": "Sherel Floranus at Antalyaspor vs Fatih Karagümrük SK 20220213.jpg",
    "url": "https://upload.wikimedia.org/wikipedia/commons/b/b1/Sherel_Floranus_at_Antalyaspor_vs_Fatih_Karag%C3%BCmr%C3%BCk_SK_20220213.jpg",
    "thumb_url": "https://upload.wikimedia.org/wikipedia/commons/b/b1/Sherel_Floranus_at_Antalyaspor_vs_Fatih_Karag%C3%BCmr%C3%BCk_SK_20220213.jpg",
    "width": 484,
    "height": 958,
    "license": "CC BY 2.0",
    "license_url": "https://creativecommons.org/licenses/by/2.0",
    "attribution": "<a rel=\"nofollow\" class=\"external text\" href=\"https://www.flickr.com/people/194383345@N04\">Antalyaspor A.Ş.</a>",
    "source": "wikidata-p18",
    "local_path": "data/photos/sherel-floranus.jpg"
  },
  "team_slug": "curaçao",
  "team_country": "Curaçao"
}
