{
  "slug": "tahsin-jamshid",
  "display_name": "Tahsin Jamshid",
  "shirt_no": null,
  "position_code": "MF",
  "dob": "2006-06-16",
  "age": 19,
  "caps": 1,
  "goals": 0,
  "club_from_squad_table": "Al-Duhail",
  "wikipedia_title": "Tahsin Jamshid",
  "date_of_birth": "2006-06-16",
  "date_of_birth_source": "wikipedia-squad-table",
  "current_club": "Al-Duhail",
  "current_club_source": "wikipedia-squad-table",
  "wikidata_qid": "Q126258395",
  "qid": "Q126258395",
  "name": "Tahsin Mohammed Jamshid",
  "description": "Qatari footballer (born 2006)",
  "wikipedia_url": "https://en.wikipedia.org/wiki/Tahsin_Jamshid",
  "wikidata_date_of_birth": "2006-01-01",
  "photo": {
    "source": "wikimedia-reviewed-none",
    "unavailable_reason": "No clean Wikimedia Commons photo, Wikidata P18 image, or Wikipedia pageimage found by verifier as of 2026-05-24."
  },
  "team_slug": "qatar",
  "team_country": "Qatar"
}
