{
  "slug": "\u00e9dier-ocampo",
  "display_name": "\u00c9dier Ocampo",
  "shirt_no": null,
  "position_code": "DF",
  "dob": "2003-03-10",
  "age": 23,
  "caps": 0,
  "goals": 0,
  "club_from_squad_table": "Vancouver Whitecaps FC",
  "wikipedia_title": "\u00c9dier Ocampo",
  "date_of_birth": "2003-03-10",
  "date_of_birth_source": "wikipedia-squad-table",
  "current_club": "Vancouver Whitecaps FC",
  "current_club_source": "wikipedia-squad-table",
  "wikidata_qid": "Q118207303",
  "qid": "Q118207303",
  "name": "\u00c9dier Ocampo",
  "description": "Colombian footballer",
  "place_of_birth_qid": "Q1005555",
  "citizenship_qids": [
    "Q739"
  ],
  "height_cm": 173.0,
  "position_qids": [
    "Q336286"
  ],
  "wikipedia_url": "https://en.wikipedia.org/wiki/%C3%89dier_Ocampo",
  "transfermarkt_id": "958473",
  "wikidata_date_of_birth": "2003-10-03",
  "positions": [
    "defender"
  ],
  "citizenship": [
    "Colombia"
  ],
  "place_of_birth": "Tumaco",
  "team_slug": "colombia",
  "team_country": "Colombia",
  "photo": {
    "source": "wikimedia-reviewed-none",
    "unavailable_reason": "No clean Wikimedia Commons photo, Wikidata P18 image, or Wikipedia pageimage found by verifier as of 2026-05-24."
  }
}
